wecom_app_svr/__init__.py
wecom_app_svr/app.py
wecom_app_svr/passive_rsp_msg.py
wecom_app_svr/req_msg.py
wecom_app_svr-0.1.0.dist-info/METADATA
wecom_app_svr-0.1.0.dist-info/WHEEL
wecom_app_svr-0.1.0.dist-info/RECORD
