Metadata-Version: 2.3
Name: wecom-app-svr
Version: 0.1.0
Summary: WeCom App Callback Server Simple Framework
Project-URL: Homepage, https://github.com/easy-wx/wecom-app-svr
Project-URL: Issues, https://github.com/easy-wx/wecom-app-svr/issues
Author-email: panzhongxian <panzhongxian0532@gmail.com>
Classifier: License :: OSI Approved :: MIT License
Classifier: Operating System :: OS Independent
Classifier: Programming Language :: Python :: 3
Requires-Python: >=3.8
Requires-Dist: flask>=3.0.0
Requires-Dist: wx-crypt>=0.0.2
